SOC/Lab2/Counter/counter.v
// Counter is a simple up counter with enable and reset
module counter #(
    parameter WIDTH = 8
)(
    input  wire                 clk,
    input  wire                 rst_n,   // active-low synchronous reset
    input  wire                 en,      // enable count when high
    input  wire                 dir,     // 1 = up, 0 = down (可选)
    input  wire [WIDTH-1:0]     load,    // parallel load data
    input  wire                 ld,      // load when high (synchronous)
    output reg  [WIDTH-1:0]     q
);

    always @(posedge clk) begin
        if (!rst_n) begin
            q <= {WIDTH{1'b0}};
        end else if (ld) begin
            q <= load;
        end else if (en) begin
            if (dir)
                q <= q + 1'b1;
            else
                q <= q - 1'b1;
        end
    end

endmodule

SOC/Lab2/Counter/counter_tb.v
`timescale 1ns/1ps

module counter_tb;
    reg clk = 0;
    reg rst_n;
    reg en;
    reg dir;
    reg [7:0] load;
    reg ld;
    wire [7:0] q;

    // Instantiate
    counter #(.WIDTH(8)) uut (
        .clk(clk),
        .rst_n(rst_n),
        .en(en),
        .dir(dir),
        .load(load),
        .ld(ld),
        .q(q)
    );

    // clock
    always #5 clk = ~clk; // 100 MHz -> period 10 ns

    initial begin
        $dumpfile("counter.vcd");
        $dumpvars(0, counter_tb);

        // reset
        rst_n = 0; en = 0; dir = 1; load = 8'hAA; ld = 0;
        #20;
        rst_n = 1;

        // count up
        en = 1; dir = 1;
        #200;

        // load a value
        ld = 1; load = 8'h10;
        #10; ld = 0;

        // count down
        dir = 0;
        #100;

        $finish;
    end
endmodule

SOC/Lab2/Counter/counter.sim/sim_1/behav/xsim/counter.vcd
$date
   Tue Sep 23 10:46:31 2025
$end

$version
  2024.1
  $dumpfile ("counter.vcd") 
$end

$timescale
  1ps
$end

$scope module counter_tb $end
$var reg 1 ! clk $end
$var reg 1 " rst_n $end
$var reg 1 # en $end
$var reg 1 $ dir $end
$var reg 8 % load [7:0] $end
$var reg 1 & ld $end
$var wire 8 ' q [7:0] $end
$scope module uut $end
$var wire 1 ( clk $end
$var wire 1 ) rst_n $end
$var wire 1 * en $end
$var wire 1 + dir $end
$var wire 8 , load [7:0] $end
$var wire 1 - ld $end
$var reg 8 . q [7:0] $end
$upscope $end
$upscope $end
$enddefinitions $end

#0
$dumpvars
0!
0"
0#
1$
b10101010 %
0&
bx '
0(
0)
0*
1+
b10101010 ,
0-
bx .
$end

#5000
1!
b0 '
1(
b0 .

#10000
0!
0(

#15000
1!
1(

#20000
0!
1"
1#
0(
1)
1*

#25000
1!
b1 '
1(
b1 .

#30000
0!
0(

#35000
1!
b10 '
1(
b10 .

#40000
0!
0(

#45000
1!
b11 '
1(
b11 .

#50000
0!
0(

#55000
1!
b100 '
1(
b100 .

#60000
0!
0(

#65000
1!
b101 '
1(
b101 .

#70000
0!
0(

#75000
1!
b110 '
1(
b110 .

#80000
0!
0(

#85000
1!
b111 '
1(
b111 .

#90000
0!
0(

#95000
1!
b1000 '
1(
b1000 .

#100000
0!
0(

#105000
1!
b1001 '
1(
b1001 .

#110000
0!
0(

#115000
1!
b1010 '
1(
b1010 .

#120000
0!
0(

#125000
1!
b1011 '
1(
b1011 .

#130000
0!
0(

#135000
1!
b1100 '
1(
b1100 .

#140000
0!
0(

#145000
1!
b1101 '
1(
b1101 .

#150000
0!
0(

#155000
1!
b1110 '
1(
b1110 .

#160000
0!
0(

#165000
1!
b1111 '
1(
b1111 .

#170000
0!
0(

#175000
1!
b10000 '
1(
b10000 .

#180000
0!
0(

#185000
1!
b10001 '
1(
b10001 .

#190000
0!
0(

#195000
1!
b10010 '
1(
b10010 .

#200000
0!
0(

#205000
1!
b10011 '
1(
b10011 .

#210000
0!
0(

#215000
1!
b10100 '
1(
b10100 .

#220000
0!
b10000 %
1&
0(
b10000 ,
1-

#225000
1!
b10000 '
1(
b10000 .

#230000
0!
0$
0&
0(
0+
0-

#235000
1!
b1111 '
1(
b1111 .

#240000
0!
0(

#245000
1!
b1110 '
1(
b1110 .

#250000
0!
0(

#255000
1!
b1101 '
1(
b1101 .

#260000
0!
0(

#265000
1!
b1100 '
1(
b1100 .

#270000
0!
0(

#275000
1!
b1011 '
1(
b1011 .

#280000
0!
0(

#285000
1!
b1010 '
1(
b1010 .

#290000
0!
0(

#295000
1!
b1001 '
1(
b1001 .

#300000
0!
0(

#305000
1!
b1000 '
1(
b1000 .

#310000
0!
0(

#315000
1!
b111 '
1(
b111 .

