SOC/Lab2/Stack/stack.v
module stack #(
    parameter DATA_WIDTH = 8,
    parameter STACK_DEPTH = 16,
    parameter ADDR_WIDTH = $clog2(STACK_DEPTH)
)(
    input wire clk,
    input wire rst_n,
    input wire [DATA_WIDTH-1:0] d,
    input wire [1:0] op,
    output reg [DATA_WIDTH-1:0] q_top,
    output reg [ADDR_WIDTH-1:0] sp,
    output wire stack_full,
    output wire stack_empty
);

    localparam LOAD = 2'b00;
    localparam PUSH = 2'b01;
    localparam POP = 2'b10;
    localparam LOAD_PUSH = 2'b11;

    reg [DATA_WIDTH-1:0] q [0:STACK_DEPTH-1];

    assign stack_full = (sp == STACK_DEPTH - 1);
    assign stack_empty = (sp == 0);
    assign q_top = q[0];

    always @(posedge clk or negedge rst_n) begin
        if (!rst_n) begin
            sp <= 0;
            for (int i = 0; i < STACK_DEPTH; i++) begin
                q[i] <= 0;
            end
        end else begin
            case (op)
                LOAD: begin
                    q[0] <= d;
                    q[1] <= q[0];
                    q[2] <= q[1];
                    q[3] <= q[2];
                    for (int i = 4; i < STACK_DEPTH; i++) begin
                        q[i] <= q[i-1];
                    end
                end

                PUSH: begin
                    if (!stack_full) begin
                        for (int i = STACK_DEPTH-1; i > 0; i--) begin
                            q[i] <= q[i-1];
                        end
                        q[0] <= d;
                        sp <= sp + 1;
                    end
                end

                POP: begin
                    if (!stack_empty) begin
                        for (int i = 0; i < STACK_DEPTH-1; i++) begin
                            q[i] <= q[i+1];
                        end
                        q[STACK_DEPTH-1] <= 0;
                        sp <= sp - 1;
                    end
                end

                LOAD_PUSH: begin
                    if (!stack_full) begin
                        for (int i = STACK_DEPTH-1; i > 0; i--) begin
                            q[i] <= q[i-1];
                        end
                        q[0] <= d;
                        sp <= sp + 1;
                    end
                end

                default: begin
                end
            endcase
        end
    end

endmodule

SOC/Lab2/Stack/stack_tb.v
`timescale 1ns / 1ps

module stack_tb();

    parameter DATA_WIDTH = 8;
    parameter STACK_DEPTH = 4;
    parameter ADDR_WIDTH = 2;

    reg clk;
    reg rst_n;
    reg [DATA_WIDTH-1:0] d;
    reg [1:0] op;
    wire [DATA_WIDTH-1:0] q_top;
    wire [ADDR_WIDTH-1:0] sp;
    wire stack_full;
    wire stack_empty;

    localparam LOAD = 2'b00;
    localparam PUSH = 2'b01;
    localparam POP = 2'b10;
    localparam LOAD_PUSH = 2'b11;

    stack #(
        .DATA_WIDTH(DATA_WIDTH),
        .STACK_DEPTH(STACK_DEPTH),
        .ADDR_WIDTH(ADDR_WIDTH)
    ) dut (
        .clk(clk),
        .rst_n(rst_n),
        .d(d),
        .op(op),
        .q_top(q_top),
        .sp(sp),
        .stack_full(stack_full),
        .stack_empty(stack_empty)
    );

    always #5 clk = ~clk;

    initial begin
        $dumpfile("stack_test.vcd");
        $dumpvars(0, stack_tb);

        clk = 0;
        rst_n = 0;
        d = 0;
        op = 0;

        #10;
        rst_n = 1;

        $display("=== Stack Operations Test ===");
        $display("Time\tOp\tData\tq_top\tSP\tFull\tEmpty");

        #10;
        d = 8'hAA;
        op = LOAD;
        #10;
        $display("%0t\tLOAD\t%h\t%h\t%d\t%b\t%b", $time, d, q_top, sp, stack_full, stack_empty);

        #10;
        d = 8'hBB;
        op = PUSH;
        #10;
        $display("%0t\tPUSH\t%h\t%h\t%d\t%b\t%b", $time, d, q_top, sp, stack_full, stack_empty);

        #10;
        d = 8'hCC;
        op = PUSH;
        #10;
        $display("%0t\tPUSH\t%h\t%h\t%d\t%b\t%b", $time, d, q_top, sp, stack_full, stack_empty);

        #10;
        op = POP;
        #10;
        $display("%0t\tPOP\t%h\t%h\t%d\t%b\t%b", $time, d, q_top, sp, stack_full, stack_empty);

        #10;
        d = 8'hDD;
        op = LOAD_PUSH;
        #10;
        $display("%0t\tL&P\t%h\t%h\t%d\t%b\t%b", $time, d, q_top, sp, stack_full, stack_empty);

        #10;
        op = POP;
        #10;
        $display("%0t\tPOP\t%h\t%h\t%d\t%b\t%b", $time, d, q_top, sp, stack_full, stack_empty);

        #20;
        $display("=== Test Complete ===");
        $finish;
    end

endmodule

SOC/Lab2/Stack/Stack.sim/sim_1/behav/xsim/stack_test.vcd
$date
   Wed Sep 24 23:08:09 2025
$end

$version
  2024.1
  $dumpfile ("stack_test.vcd") 
$end

$timescale
  1ps
$end

$scope module stack_tb $end
$var reg 1 ! clk $end
$var reg 1 " rst_n $end
$var reg 8 # d [7:0] $end
$var reg 2 $ op [1:0] $end
$var wire 8 % q_top [7:0] $end
$var wire 2 & sp [1:0] $end
$var wire 1 ' stack_full $end
$var wire 1 ( stack_empty $end
$scope module dut $end
$var wire 1 ) clk $end
$var wire 1 * rst_n $end
$var wire 8 + d [7:0] $end
$var wire 2 , op [1:0] $end
$var wire 8 % q_top [7:0] $end
$var reg 2 - sp [1:0] $end
$var wire 1 ' stack_full $end
$var wire 1 ( stack_empty $end
$var integer 32 . i [31:0] $end
$upscope $end
$upscope $end
$enddefinitions $end

#0
$dumpvars
0!
0"
b0 #
b0 $
b0 %
b0 &
0'
1(
0)
0*
b0 +
b0 ,
b0 -
b100 .
$end

#5000
1!
1)
b100 .

#10000
0!
1"
0)
1*

#15000
1!
1)

#20000
0!
b10101010 #
0)
b10101010 +

#25000
1!
b10101010 %
1)

#30000
0!
0)

#35000
1!
1)

#40000
0!
b10111011 #
b1 $
0)
b10111011 +
b1 ,

#45000
1!
b10111011 %
b1 &
0(
1)
b1 -
b0 .

#50000
0!
0)

#55000
1!
b10 &
1)
b10 -
b0 .

#60000
0!
b11001100 #
0)
b11001100 +

#65000
1!
b11001100 %
b11 &
1'
1)
b11 -
b0 .

#70000
0!
0)

#75000
1!
1)

#80000
0!
b10 $
0)
b10 ,

#85000
1!
b10111011 %
b10 &
0'
1)
b10 -
b11 .

#90000
0!
0)

#95000
1!
b1 &
1)
b1 -
b11 .

#100000
0!
b11011101 #
b11 $
0)
b11011101 +
b11 ,

#105000
1!
b11011101 %
b10 &
1)
b10 -
b0 .

#110000
0!
0)

#115000
1!
b11 &
1'
1)
b11 -
b0 .

#120000
0!
b10 $
0)
b10 ,

#125000
1!
b10 &
0'
1)
b10 -
b11 .

#130000
0!
0)

#135000
1!
b10111011 %
b1 &
1)
b1 -
b11 .

#140000
0!
0)

#145000
1!
b10101010 %
b0 &
1(
1)
b0 -
b11 .
